{"resourceType":"ValueSet","id":"valueset-ecr-messageheader-event","meta":{"versionId":"3","lastUpdated":"2020-11-25T23:10:42.027+00:00","source":"#ENvb1PjzTspuI7IT"},"text":{"status":"extensions","div":"<div xmlns=\"http://www.w3.org/1999/xhtml\"><ul><li>Include these codes as defined in <a href=\"CodeSystem-codesystem-messageHeader-event.html\"><code>http://hl7.org/fhir/us/ecr/CodeSystem/codesystem-messageHeader-event</code></a><table class=\"none\"><tr><td style=\"white-space:nowrap\"><b>Code</b></td><td><b>Display</b></td><td><b>Definition</b></td></tr><tr><td><a href=\"CodeSystem-codesystem-messageHeader-event.html#codesystem-messageHeader-event-process-eicr\">process-eicr</a></td><td>Process eICR</td><td>Process the eICR that is the focus of the eCR Task referenced by the eCR MessageHeader. See the Electronic Initial Case Report (eICR) Transaction and Profiles page in the eCR IG for further details.</td></tr><tr><td><a href=\"CodeSystem-codesystem-messageHeader-event.html#codesystem-messageHeader-event-process-rr\">process-rr</a></td><td>Process Reportability Response</td><td>Process the Reportability Response that is the focus of the eCR Task referenced by the eCR MessageHeader. See the Reportability Response (RR) Transaction and Profiles page in the eCR IG for further details.</td></tr></table></li></ul></div>"},"url":"http://hl7.org/fhir/us/ecr/ValueSet/valueset-ecr-messageheader-event","version":"1.1.0","name":"ValueSet_Ecr_MessageHeader_Event","title":"eCR MessageHeader Event Value Set","status":"active","date":"2021-04-27T00:39:36+00:00","publisher":"HL7 Public Health Work Group (http://www.hl7.org/Special/committees/pher/index.cfm)","contact":[{"name":"HL7 International - Public Health","telecom":[{"system":"url","value":"http://www.hl7.org/Special/committees/pher"}]}],"description":"This value set contains codes that identify the event an eCR message represents.","jurisdiction":[{"coding":[{"system":"urn:iso:std:iso:3166","code":"US","display":"United States of America"}],"text":"United States of America"}],"compose":{"inactive":false,"include":[{"system":"http://hl7.org/fhir/us/ecr/CodeSystem/codesystem-messageHeader-event","concept":[{"code":"process-eicr","display":"Process eICR"},{"code":"process-rr","display":"Process Reportability Response"}]}]}}